mpsmqutils/__init__.py
mpsmqutils/log_wrapper.py
mpsmqutils/messagehandler.py
mpsmqutils/mqutils.py
mpsmqutils/tests/__init__.py
mpsmqutils/tests/test_mqutils.py
lts_mpsmqutils-2.1.2.dist-info/METADATA
lts_mpsmqutils-2.1.2.dist-info/WHEEL
lts_mpsmqutils-2.1.2.dist-info/top_level.txt
lts_mpsmqutils-2.1.2.dist-info/RECORD
