Metadata-Version: 2.2
Name: lts-mpsmqutils
Version: 2.1.2
Summary: A set of utilities for communicating with a message queue
Home-page: https://github.huit.harvard.edu/LTS/mps-mqutils
Classifier: Programming Language :: Python :: 3
Classifier: License :: OSI Approved :: MIT License
Classifier: Operating System :: OS Independent
Requires-Python: >=3.6
Requires-Dist: lts-mpsjobtracker-mongo
Requires-Dist: requests
Requires-Dist: pytest
Requires-Dist: tenacity
Requires-Dist: cryptography
Dynamic: classifier
Dynamic: description
Dynamic: description-content-type
Dynamic: home-page
Dynamic: requires-dist
Dynamic: requires-python
Dynamic: summary
